cli.py
gpt_clip-0.2.2.dist-info/licenses/LICENSE
gpt_clip-0.2.2.dist-info/METADATA
gpt_clip-0.2.2.dist-info/WHEEL
gpt_clip-0.2.2.dist-info/entry_points.txt
gpt_clip-0.2.2.dist-info/top_level.txt
gpt_clip-0.2.2.dist-info/RECORD
