Metadata-Version: 2.4
Name: gpt-clip
Version: 0.2.2
Summary: Send clipboard content to OpenAI Chat API and copy response back to clipboard.
Home-page: 
Author: 
Author-email: 
Classifier: Programming Language :: Python :: 3
Classifier: Environment :: Console
Classifier: Operating System :: OS Independent
Requires-Python: >=3.7
License-File: LICENSE
Requires-Dist: openai>=0.27.7
Requires-Dist: pyperclip
Dynamic: classifier
Dynamic: description
Dynamic: description-content-type
Dynamic: license-file
Dynamic: requires-dist
Dynamic: requires-python
Dynamic: summary
